acnutils/__init__.py
acnutils/db.py
acnutils/py.typed
acnutils-0.6.3.dist-info/COPYING
acnutils-0.6.3.dist-info/METADATA
acnutils-0.6.3.dist-info/WHEEL
acnutils-0.6.3.dist-info/RECORD
