Metadata-Version: 2.1
Name: acnutils
Version: 0.6.3
Summary: Various utilities used in AntiCompositeNumber's bots
Home-page: https://github.com/AntiCompositeNumber/acnutils
License: GPL-3.0-or-later
Keywords: pywikibot,toolforge,wikimedia,wikipedia
Author: AntiCompositeNumber
Author-email: anticompositenumber+pypi@gmail.com
Requires-Python: >=3.9,<4.0
Classifier: Development Status :: 4 - Beta
Classifier: Environment :: Console
Classifier: Intended Audience :: Developers
Classifier: License :: OSI Approved :: GNU General Public License v3 or later (GPLv3+)
Classifier: Operating System :: OS Independent
Classifier: Programming Language :: Python :: 3
Classifier: Programming Language :: Python :: 3.9
Classifier: Programming Language :: Python :: 3.10
Classifier: Programming Language :: Python :: 3.11
Classifier: Programming Language :: Python :: 3.12
Classifier: Topic :: Internet :: WWW/HTTP :: Dynamic Content :: Wiki
Classifier: Topic :: Software Development :: Libraries :: Python Modules
Classifier: Topic :: Utilities
Classifier: Typing :: Typed
Provides-Extra: db
Requires-Dist: pywikibot (>=6.6.1,<10.0.0)
Requires-Dist: toolforge (>=5,<7) ; extra == "db"
Project-URL: Repository, https://github.com/AntiCompositeNumber/acnutils
